onlconvert.py
onlconvert-0.0.1.dist-info/WHEEL
onlconvert-0.0.1.dist-info/METADATA
onlconvert-0.0.1.dist-info/RECORD
